locidex/__init__.py
locidex/build.py
locidex/constants.py
locidex/extract.py
locidex/format.py
locidex/main.py
locidex/manifest.py
locidex/merge.py
locidex/report.py
locidex/search.py
locidex/utils.py
locidex/version.py
locidex/classes/__init__.py
locidex/classes/aligner.py
locidex/classes/assignment.py
locidex/classes/blast.py
locidex/classes/db.py
locidex/classes/extractor.py
locidex/classes/fasta.py
locidex/classes/gbk.py
locidex/classes/gff.py
locidex/classes/mafft.py
locidex/classes/metadata.py
locidex/classes/prodigal.py
locidex/classes/seq_intake.py
locidex/classes/seq_writers.py
locidex/example/__init__.py
locidex-0.4.0.dist-info/licenses/LICENSE
locidex-0.4.0.dist-info/METADATA
locidex-0.4.0.dist-info/WHEEL
locidex-0.4.0.dist-info/entry_points.txt
locidex-0.4.0.dist-info/top_level.txt
locidex-0.4.0.dist-info/RECORD
