Metadata-Version: 2.4
Name: locidex
Version: 0.4.0
Summary: Genomic Address Service: De novo clustering and cluster address assignment
Home-page: https://github.com/phac-nml/locidex
Author: James Robertson
Author-email: james.robertson@phac-aspc.gc.ca
License: GPLv3
Keywords: cgMLST,wgMLST,outbreak,surveillance,blast,antimicrobial resistance,amr,virulence
Classifier: Development Status :: 4 - Beta
Classifier: Environment :: Console
Classifier: License :: OSI Approved :: GNU General Public License v3 or later (GPLv3+)
Classifier: Intended Audience :: Science/Research
Classifier: Topic :: Scientific/Engineering
Classifier: Topic :: Scientific/Engineering :: Bio-Informatics
Classifier: Programming Language :: Python
Classifier: Programming Language :: Python :: 3.8
Classifier: Programming Language :: Python :: 3.9
Classifier: Programming Language :: Python :: Implementation :: CPython
Classifier: Operating System :: POSIX :: Linux
Requires-Python: >=3.8.2,<4
License-File: LICENSE
Requires-Dist: numba>=0.57.1
Requires-Dist: numpy>=1.24.4
Requires-Dist: tables>=3.8.0
Requires-Dist: six>=1.16.0
Requires-Dist: pandas>=2.0.2
Requires-Dist: biopython>=1.83
Requires-Dist: pyrodigal>=3.0.0
Dynamic: author
Dynamic: author-email
Dynamic: classifier
Dynamic: home-page
Dynamic: keywords
Dynamic: license
Dynamic: license-file
Dynamic: requires-dist
Dynamic: requires-python
Dynamic: summary
